pydict.py
pydict_cedar-0.0.3.dist-info/LICENSE
pydict_cedar-0.0.3.dist-info/METADATA
pydict_cedar-0.0.3.dist-info/WHEEL
pydict_cedar-0.0.3.dist-info/top_level.txt
pydict_cedar-0.0.3.dist-info/RECORD
